signoffs/__init__.py
signoffs/approvals.py
signoffs/apps.py
signoffs/forms.py
signoffs/models.py
signoffs/process.py
signoffs/registry.py
signoffs/settings.py
signoffs/shortcuts.py
signoffs/signing_order.py
signoffs/signoffs.py
signoffs/urls.py
signoffs/views.py
signoffs/contrib/__init__.py
signoffs/contrib/approvals/__init__.py
signoffs/contrib/approvals/approvals.py
signoffs/contrib/approvals/apps.py
signoffs/contrib/approvals/forms.py
signoffs/contrib/approvals/models.py
signoffs/contrib/approvals/migrations/0001_initial.py
signoffs/contrib/approvals/migrations/__init__.py
signoffs/contrib/signets/__init__.py
signoffs/contrib/signets/apps.py
signoffs/contrib/signets/models.py
signoffs/contrib/signets/signoffs.py
signoffs/contrib/signets/migrations/0001_initial.py
signoffs/contrib/signets/migrations/__init__.py
signoffs/core/__init__.py
signoffs/core/approvals.py
signoffs/core/forms.py
signoffs/core/process.py
signoffs/core/signoffs.py
signoffs/core/utils.py
signoffs/core/models/__init__.py
signoffs/core/models/fields.py
signoffs/core/models/managers.py
signoffs/core/models/signets.py
signoffs/core/models/stamps.py
signoffs/core/renderers/__init__.py
signoffs/core/renderers/approvals.py
signoffs/core/renderers/helpers.py
signoffs/core/renderers/process.py
signoffs/core/renderers/signoffs.py
signoffs/core/signing_order/__init__.py
signoffs/core/signing_order/regex_match.py
signoffs/core/signing_order/signing_order.py
signoffs/core/signing_order/signoff_pattern.py
signoffs/core/signing_order/tests/__init__.py
signoffs/core/signing_order/tests/test_regex_match.py
signoffs/core/signing_order/tests/test_signoff_pattern.py
signoffs/core/status/__init__.py
signoffs/core/status/approvals.py
signoffs/core/tests/__init__.py
signoffs/core/tests/fixtures.py
signoffs/core/tests/models.py
signoffs/core/tests/test_approval_fields.py
signoffs/core/tests/test_approval_models.py
signoffs/core/tests/test_approval_process.py
signoffs/core/tests/test_process.py
django_signoffs-0.3.12.dist-info/LICENSE
django_signoffs-0.3.12.dist-info/METADATA
django_signoffs-0.3.12.dist-info/WHEEL
django_signoffs-0.3.12.dist-info/entry_points.txt
django_signoffs-0.3.12.dist-info/top_level.txt
django_signoffs-0.3.12.dist-info/RECORD
