Metadata-Version: 2.1
Name: django_signoffs
Version: 0.3.12
Summary: A mico-framework for collecting lightweight, non-crypto "signatures" for virtually anything.
Author-email: Joseph Fall <powderflask@gmail.com>
License: MIT License
Project-URL: Homepage, https://github.com/powderflask/django-signoffs
Project-URL: Repository, https://github.com/powderflask/django-signoffs
Project-URL: Documentation, https://django-signoffs.readthedocs.io
Keywords: django-signoffs
Classifier: Development Status :: 2 - Pre-Alpha
Classifier: License :: OSI Approved :: MIT License
Classifier: Intended Audience :: Developers
Classifier: Natural Language :: English
Classifier: Programming Language :: Python :: 3
Classifier: Framework :: Django
Requires-Python: <4.0,>=3.8
License-File: LICENSE
Requires-Dist: django<5.0,>=3.2
Requires-Dist: persisting-theory
Requires-Dist: regex
Provides-Extra: fsm
Requires-Dist: django-fsm<=3.0.0,>=2.8; extra == "fsm"
Provides-Extra: docs
Requires-Dist: sphinx; extra == "docs"
Requires-Dist: myst-parser; extra == "docs"
Requires-Dist: furo; extra == "docs"
Requires-Dist: linkify-it-py; extra == "docs"
Requires-Dist: sphinxcontrib_django; extra == "docs"
Requires-Dist: sphinx-autodoc2; extra == "docs"
Provides-Extra: style
Requires-Dist: black; extra == "style"
Requires-Dist: isort; extra == "style"
Requires-Dist: flake8; extra == "style"
Requires-Dist: flake8-bugbear; extra == "style"
Provides-Extra: test
Requires-Dist: tox; extra == "test"
Requires-Dist: pytest; extra == "test"
Requires-Dist: pytest-django; extra == "test"
Requires-Dist: pytest-cov; extra == "test"
Requires-Dist: pytest-sugar; extra == "test"
Provides-Extra: utils
Requires-Dist: invoke; extra == "utils"
Requires-Dist: bumpver; extra == "utils"
Requires-Dist: build; extra == "utils"
Requires-Dist: twine; extra == "utils"
Requires-Dist: pip-tools; extra == "utils"
